flask_sse.py
flask_sse_datastar-0.1.0.dist-info/LICENSE
flask_sse_datastar-0.1.0.dist-info/METADATA
flask_sse_datastar-0.1.0.dist-info/WHEEL
flask_sse_datastar-0.1.0.dist-info/top_level.txt
flask_sse_datastar-0.1.0.dist-info/RECORD
