Metadata-Version: 2.1
Name: flask-sse-datastar
Version: 0.1.0
Summary: Server-Sent Events for Flask
Home-page: https://github.com/singingwolfboy/flask-sse
Author: David Baumgold
Author-email: Michael McDougal <michael.93.mcdougal@gmail.com>
License: MIT
Project-URL: Homepage, https://github.com/Amatuon/flask-sse-datastar
Classifier: License :: OSI Approved :: MIT License
Classifier: Framework :: Flask
Classifier: Programming Language :: Python
Classifier: Programming Language :: Python :: 3
Classifier: Programming Language :: Python :: 3.5
Requires-Python: >=3.5
License-File: LICENSE
Requires-Dist: flask >=0.9
Requires-Dist: redis
Requires-Dist: six
